nm/__init__.py
nm-0.0.5.dist-info/licenses/LICENSE
nm-0.0.5.dist-info/METADATA
nm-0.0.5.dist-info/WHEEL
nm-0.0.5.dist-info/top_level.txt
nm-0.0.5.dist-info/RECORD
