Metadata-Version: 2.4
Name: nm
Version: 0.0.5
Summary: SOM utils
Home-page: https://github.com/t-c-w/nm
Author: Thor Whalen
License: apache-2.0
Platform: any
License-File: LICENSE
Dynamic: license-file
